<?xml version="1.0"?>
<!-- DO NOT CHANGE THIS FILE!! IT WAS GENERATED AUTOMATICALLY! (you must edit files in help_template directory) -->
<Document style="helpdocument">
	<p style="htitle">ЛЭП</p>
	<p style="hp">Линии электропередач (ЛЭП) передают электроэнергию от солнечных и угольных электростанций, а также продвинутых ветрогенераторов, подстанциям и в промзоны. ЛЭП должны подсоединяться к верхнему левому углу построек, которым необходима энергия.</p>
	<p style="hp">ЛЭП могут проходить <b>над</b> грунтовками, дорогами, рельсами и реками (но не более одного участка). Если они расположены по обе стороны транспортной системы или реки, они действуют как будто они соединены. Вам иногда придётся закапывать небольшие участки рек, чтобы соединить ЛЭП -- но помните, это очень дорого. ЛЭП соединены между собой, когда они выровнены и видна передача электроэнергии по проводам.</p>

  <p style="hp">Это ЛЭП:</p>
   <img src="images/tiles/powerlvd.png" halign="center"/>

  <p style="hp">Это иконка:</p>
   <img src="images/gui/buttonpanel/power/powerlines.png" halign="center"/>

  <p style="hp">так выглядит на миникарте:</p>
   <img src="images/gui/mapview/roundbuttons/round_electrics.png" halign="center"/>

  <p style="hsubtitle">См. ещё:</p>
	<li><a href="power">Энергия</a></li>
	<li><a href="substation">Подстанция</a></li>
	<li><a href="windmill">Ветрогенератор</a></li>
	<li><a href="powerscoal">Угольная электростанция</a></li>
	<li><a href="powerssolar">Солнечная электростанция</a></li>
	<li><a href="msb-power">Зоны электроснабжения</a></li>
</Document>
