<?xml version="1.0"?>
<Document style="helpdocument">
	<p style="htitle">Obair</p>
	<p style="hp">Solairidh daoine a bhios a' fuireach ann an còmhnaidh obair. Chleachdaidh a' mhòrchuid a raointean obair ach an obraich iad. Chan eil cuid a raointean a leithid carraighean feumach air obair ach fhad 's a thèid an togail.</p>
	<p style="hp">'S urrainn dha mhargaidean obair a sholar nuair a bhios tu air margaid a thogail am fagas an raoin a bhios feumach air obair. Feumaidh a' mhargaid an obair fhaighinn o àite air choireigin co-dhiù 's tha dà dhòigh ann: air an dàrna làimh, ma tha còmhnaidh am fagas na margaid, solairidh e obair dhan mhargaid an coimeas ris an t-sluagh a bhios a' fuireach ann is na h-àireamh de mhargaidean a cho-roinneas an obair. 'S e giùlan a tha san dòigh eile. Ma tha barrachd obrach aig margaid na tha i feumach air, cuiridh i cuid dhiubh air a' ghiùlan. Gheibh margaid sam bith a bhios ceangailte ris a' ghiùlan traca, rathaid no rèile greim air an obair ma bhios i feumach oirre.</p>
	<p style="hp">Ma dh'fhàsas magaid "làn" de dh'obair cha ghabh i rithe tuilleadh o chòmhnaidhean. Bidh daoine gun chosnadh ann nuair a thachras seo is gun mhargaid nach eil làn am fagas.</p>
	<p style="hp">Cuiridh ionad-slàinte am fagas còmhnaidh ris an uiread de dh'obair a thèid a sholar do mhagaidean ionadail.</p>

	<p style="hsubtitle">Faic cuideachd:</p>
	<li><a href="commodities">Bathar-amh</a></li>
	<li><a href="residential">Còmhnaidhean</a></li>
	<li><a href="transport">Giùlan</a></li>
	<li><a href="market">Margaid</a></li>
</Document>
