<?xml version="1.0" encoding="UTF-8"?>
<Document style="helpdocument">
<p style="htitle">Oideachadh - Cnàmh-sgeul</p>
<p style="hp">Fo "Geama ùr" </p>

<p style="hsubtitle">Furasta</p>
<li>Deagh amannan</li>

<li>Tràigh (cuimhnich gum faigh do mhuinntir bàs gun bhiadh ;-) </li>

<p style="hsubtitle">Doirbh</p>
<li>"droch amannan": feuch gun seachnaich thu bristeachas. Feumaidh tu sgrùdadh mionaideach a dhèanamh air a' bhaile agus ceumannan èiginneach a chur romhad gus cosgaisean a sheachnadh ach am faigh thu airgead. Tha e doirbh ach gabh e dèanamh fiù 's gun ruig thu eaconamaidh seasmhach.</li>
<li>"glè thioram": chan eil ach glè bheag de dh'uisge air an tìr, mar sin feumaidh tu taghadh gu cùramach far an cuir thu na tuathanasan agus na coilltean agad airson an èifeachdachd as motha.</li>
<li>"glè fhliuch": tha cha mhòr an dùthaich gu lèor fo thuil, mar sin tha e glè dhoirbh baile a thogail.</li>
<p style="hp"></p>
</Document>
